<?xml version="1.0" encoding="UTF-8"?>
<metadata xml:lang="en"><Esri><CreaDate>20190305</CreaDate><CreaTime>16432100</CreaTime><ArcGISFormat>1.0</ArcGISFormat><SyncOnce>TRUE</SyncOnce><DataProperties><lineage><Process Name="Define Projection" ToolSource="c:\program files (x86)\arcgis\desktop10.6\ArcToolbox\Toolboxes\Data Management Tools.tbx\DefineProjection" Date="20190305" Time="164321">DefineProjection G:\Coral_Suitability\Downscaling\Present_Observed_Data\pH_GMEDcurrent.tif GEOGCS['GCS_WGS_1984',DATUM['D_WGS_1984',SPHEROID['WGS_1984',6378137.0,298.257223563]],PRIMEM['Greenwich',0.0],UNIT['Degree',0.0174532925199433]]</Process><Process Name="Define Projection" ToolSource="c:\program files (x86)\arcgis\desktop10.6\ArcToolbox\Toolboxes\Data Management Tools.tbx\DefineProjection" Date="20190305" Time="170620">DefineProjection G:\Coral_Suitability\Downscaling\Present_Observed_Data\pH_GMEDcurrent.tif GEOGCS['GCS_WGS_1984',DATUM['D_WGS_1984',SPHEROID['WGS_1984',6378137.0,298.257223563]],PRIMEM['Greenwich',0.0],UNIT['Degree',0.0174532925199433]]</Process><Process Name="Define Projection (2)" ToolSource="c:\program files (x86)\arcgis\desktop10.6\ArcToolbox\Toolboxes\Data Management Tools.tbx\DefineProjection" Date="20190305" Time="170643">DefineProjection G:\Coral_Suitability\Downscaling\Present_Observed_Data\pH_GMEDcurrent.tif GEOGCS['GCS_WGS_1984',DATUM['D_WGS_1984',SPHEROID['WGS_1984',6378137.0,298.257223563]],PRIMEM['Greenwich',0.0],UNIT['Degree',0.0174532925199433]]</Process><Process Name="Define Projection" ToolSource="c:\program files (x86)\arcgis\desktop10.6\ArcToolbox\Toolboxes\Data Management Tools.tbx\DefineProjection" Date="20190305" Time="171825">DefineProjection G:\Coral_Suitability\Downscaling\Present_Observed_Data\pH_GMEDcurrent.tif GEOGCS['GCS_WGS_1984',DATUM['D_WGS_1984',SPHEROID['WGS_1984',6378137.0,298.257223563]],PRIMEM['Greenwich',0.0],UNIT['Degree',0.0174532925199433]]</Process><Process Name="Define Projection" ToolSource="c:\program files (x86)\arcgis\desktop10.6\ArcToolbox\Toolboxes\Data Management Tools.tbx\DefineProjection" Date="20190306" Time="123834">DefineProjection G:\Coral_Suitability\Downscaling\Present_Observed_Data\pH_GMEDcurrent.tif GEOGCS['GCS_WGS_1984',DATUM['D_WGS_1984',SPHEROID['WGS_1984',6378137.0,298.257223563]],PRIMEM['Greenwich',0.0],UNIT['Degree',0.0174532925199433]]</Process><Process Name="Define Projection" ToolSource="c:\program files (x86)\arcgis\desktop10.6\ArcToolbox\Toolboxes\Data Management Tools.tbx\DefineProjection" Date="20190306" Time="135211">DefineProjection G:\Coral_Suitability\Downscaling\Present_Observed_Data\pH_GMEDcurrent.tif GEOGCS['GCS_WGS_1984',DATUM['D_WGS_1984',SPHEROID['WGS_1984',6378137.0,298.257223563]],PRIMEM['Greenwich',0.0],UNIT['Degree',0.0174532925199433]]</Process><Process Name="Define Projection (5)" ToolSource="c:\program files (x86)\arcgis\desktop10.6\ArcToolbox\Toolboxes\Data Management Tools.tbx\DefineProjection" Date="20190306" Time="135304">DefineProjection G:\Coral_Suitability\Downscaling\Present_Observed_Data\pH_GMEDcurrent.tif GEOGCS['GCS_WGS_1984',DATUM['D_WGS_1984',SPHEROID['WGS_1984',6378137.0,298.257223563]],PRIMEM['Greenwich',0.0],UNIT['Degree',0.0174532925199433]]</Process><Process Name="Define Projection" ToolSource="c:\program files (x86)\arcgis\desktop10.6\ArcToolbox\Toolboxes\Data Management Tools.tbx\DefineProjection" Date="20190308" Time="145143">DefineProjection G:\Coral_Suitability\Downscaling\Present_Observed_Data\pH_GMEDcurrent.tif GEOGCS['GCS_WGS_1984',DATUM['D_WGS_1984',SPHEROID['WGS_1984',6378137.0,298.257223563]],PRIMEM['Greenwich',0.0],UNIT['Degree',0.0174532925199433]]</Process><Process Name="Define Projection (5)" ToolSource="c:\program files (x86)\arcgis\desktop10.6\ArcToolbox\Toolboxes\Data Management Tools.tbx\DefineProjection" Date="20190308" Time="145235">DefineProjection G:\Coral_Suitability\Downscaling\Present_Observed_Data\pH_GMEDcurrent.tif GEOGCS['GCS_WGS_1984',DATUM['D_WGS_1984',SPHEROID['WGS_1984',6378137.0,298.257223563]],PRIMEM['Greenwich',0.0],UNIT['Degree',0.0174532925199433]]</Process><Process Name="Define Projection" ToolSource="c:\program files (x86)\arcgis\desktop10.6\ArcToolbox\Toolboxes\Data Management Tools.tbx\DefineProjection" Date="20190308" Time="154814">DefineProjection G:\Coral_Suitability\Downscaling\Present_Observed_Data\pH_GMEDcurrent.tif GEOGCS['GCS_WGS_1984',DATUM['D_WGS_1984',SPHEROID['WGS_1984',6378137.0,298.257223563]],PRIMEM['Greenwich',0.0],UNIT['Degree',0.0174532925199433]]</Process><Process Name="Define Projection (2)" ToolSource="c:\program files (x86)\arcgis\desktop10.6\ArcToolbox\Toolboxes\Data Management Tools.tbx\DefineProjection" Date="20190308" Time="154902">DefineProjection G:\Coral_Suitability\Downscaling\Present_Observed_Data\pH_GMEDcurrent.tif GEOGCS['GCS_WGS_1984',DATUM['D_WGS_1984',SPHEROID['WGS_1984',6378137.0,298.257223563]],PRIMEM['Greenwich',0.0],UNIT['Degree',0.0174532925199433]]</Process></lineage></DataProperties></Esri></metadata>
